laserembeddings/__init__.py
laserembeddings/__main__.py
laserembeddings/data/.gitkeep
laserembeddings/embedding.py
laserembeddings/encoder.py
laserembeddings/laser.py
laserembeddings/preprocessing.py
laserembeddings/utils.py
laserembeddings_fork-1.2.2.dist-info/LICENSE
laserembeddings_fork-1.2.2.dist-info/METADATA
laserembeddings_fork-1.2.2.dist-info/WHEEL
laserembeddings_fork-1.2.2.dist-info/RECORD
